plugboard/__init__.py
plugboard/__main__.py
plugboard/py.typed
plugboard/_zmq/__init__.py
plugboard/_zmq/zmq_proxy.py
plugboard/cli/__init__.py
plugboard/cli/process/__init__.py
plugboard/component/__init__.py
plugboard/component/component.py
plugboard/component/io_controller.py
plugboard/component/utils.py
plugboard/connector/__init__.py
plugboard/connector/asyncio_channel.py
plugboard/connector/channel.py
plugboard/connector/connector.py
plugboard/connector/connector_builder.py
plugboard/connector/rabbitmq_channel.py
plugboard/connector/ray_channel.py
plugboard/connector/serde_channel.py
plugboard/connector/zmq_channel.py
plugboard/diagram/__init__.py
plugboard/diagram/diagram.py
plugboard/diagram/mermaid.py
plugboard/events/__init__.py
plugboard/events/event.py
plugboard/events/event_connector_builder.py
plugboard/events/event_handlers.py
plugboard/exceptions/__init__.py
plugboard/library/__init__.py
plugboard/library/data_reader.py
plugboard/library/data_writer.py
plugboard/library/file_io.py
plugboard/library/llm.py
plugboard/library/sql_io.py
plugboard/library/websocket_io.py
plugboard/process/__init__.py
plugboard/process/local_process.py
plugboard/process/process.py
plugboard/process/process_builder.py
plugboard/process/ray_process.py
plugboard/schemas/__init__.py
plugboard/schemas/_common.py
plugboard/schemas/component.py
plugboard/schemas/config.py
plugboard/schemas/connector.py
plugboard/schemas/entities.py
plugboard/schemas/io.py
plugboard/schemas/process.py
plugboard/schemas/state.py
plugboard/schemas/tune.py
plugboard/state/__init__.py
plugboard/state/dict_state_backend.py
plugboard/state/postgres_queries.py
plugboard/state/postgres_state_backend.py
plugboard/state/ray_state_backend.py
plugboard/state/sqlite_queries.py
plugboard/state/sqlite_state_backend.py
plugboard/state/state_backend.py
plugboard/tune/__init__.py
plugboard/tune/tune.py
plugboard/utils/__init__.py
plugboard/utils/async_utils.py
plugboard/utils/dependencies.py
plugboard/utils/di.py
plugboard-0.4.0.dist-info/METADATA
plugboard-0.4.0.dist-info/WHEEL
plugboard-0.4.0.dist-info/entry_points.txt
plugboard-0.4.0.dist-info/licenses/LICENSE
plugboard-0.4.0.dist-info/RECORD
