Metadata-Version: 2.4
Name: plugboard
Version: 0.4.0
Summary: Plugboard is an event driven modelling and orchestration framework for simulating and driving complex processes with many interconnected stateful components.
Author-email: Chris Knight <plugboard@csknight.uk>, Toby Coleman <plugboard@tobycoleman.com>
License-Expression: Apache-2.0
License-File: LICENSE
Classifier: Intended Audience :: Developers
Classifier: Intended Audience :: Science/Research
Classifier: Programming Language :: Python :: 3.12
Classifier: Programming Language :: Python :: 3.13
Classifier: Topic :: Scientific/Engineering
Classifier: Typing :: Typed
Requires-Python: <4.0,>=3.12
Requires-Dist: aio-pika<10,>=9.5.5
Requires-Dist: aiosqlite<1,>=0.20
Requires-Dist: annotated-types<1,>=0.7
Requires-Dist: async-lru<3,>=2.0
Requires-Dist: asyncpg<1,>=0.29.0
Requires-Dist: fsspec>=2024.9.0
Requires-Dist: msgspec[yaml]<1,>=0.18
Requires-Dist: pandas<3,>=1.0
Requires-Dist: pyarrow<21,>=17.0
Requires-Dist: pydantic-settings<3,>=2.7.1
Requires-Dist: pydantic<3,>=2.8
Requires-Dist: pyzmq<27,>=26.2
Requires-Dist: rich<14,>=13.9
Requires-Dist: sqlalchemy[asyncio]<3,>=2.0
Requires-Dist: structlog<26,>=25.1.0
Requires-Dist: that-depends<4,>=3.4.1
Requires-Dist: typer<1,>=0.12
Requires-Dist: uvloop<1,>=0.21.0; platform_system != 'Windows'
Provides-Extra: aws
Requires-Dist: s3fs>=2024.9.0; extra == 'aws'
Provides-Extra: azure
Requires-Dist: adlfs>=2024.7.0; extra == 'azure'
Provides-Extra: gcp
Requires-Dist: gcsfs>=2024.9.0; extra == 'gcp'
Provides-Extra: llm
Requires-Dist: llama-index-core<1,>=0.12.30; extra == 'llm'
Requires-Dist: llama-index-llms-openai<1,>=0.3.33; extra == 'llm'
Provides-Extra: ray
Requires-Dist: jsonschema<4.25.0; extra == 'ray'
Requires-Dist: optuna<4,>=3.0; extra == 'ray'
Requires-Dist: ray[default,tune]<3,>=2.47.1; extra == 'ray'
Provides-Extra: websockets
Requires-Dist: websockets<15,>=14.2; extra == 'websockets'
